{
    "activity" : "DiscriminationImages",
    "data" : [
        {
            "id"        : 0,
            "image"     : "assets/img/discrimination/arcoiris.png",
            "title"      : "Arcoiris",
            "category"  : "cielo"
        },
        {
            "id"        : 1,
            "image"     : "assets/img/discrimination/automovil.png",
            "title"      : "Automóvil",
            "category"  : "transporte"
        },
        {
            "id"        : 2,
            "image"     : "assets/img/discrimination/bicicleta.png",
            "title"      : "Bicicleta",
            "category"  : "transporte"
        },
        {
            "id"        : 3,
            "image"     : "assets/img/discrimination/bombero.png",
            "title"      : "Bombero",
            "category"  : "oficio"
        },
        {
            "id"        : 4,
            "image"     : "assets/img/discrimination/carpintero.png",
            "title"      : "Carpintero",
            "category"  : "oficio"
        },
        {
            "id"        : 5,
            "image"     : "assets/img/discrimination/estrella.png",
            "title"      : "Estrella",
            "category"  : "cielo"
        },
        {
            "id"        : 6,
            "image"     : "assets/img/discrimination/borrador.png",
            "title"      : "Borrador",
            "category"  : "papeleria"
        },
        {
            "id"        : 7,
            "image"     : "assets/img/discrimination/bufanda.png",
            "title"      : "Bufanda",
            "category"  : "prenda"
        },
        {
            "id"        : 8,
            "image"     : "assets/img/discrimination/pantalon.png",
            "title"      : "Pantalón",
            "category"  : "prenda"
        },
        {
            "id"        : 9,
            "image"     : "assets/img/discrimination/cuchara.png",
            "title"      : "Cuchara",
            "category"  : "cubierto"
        },
        {
            "id"        : 10,
            "image"     : "assets/img/discrimination/puerta.png",
            "title"      : "Puerta",
            "category"  : "madera"
        },
        {
            "id"        : 11,
            "image"     : "assets/img/discrimination/tenedor.png",
            "title"      : "Tenedor",
            "category"  : "cubierto"
        },
        {
            "id"        : 12,
            "image"     : "assets/img/discrimination/mesa.png",
            "title"      : "Mesa",
            "category"  : "madera"
        },
        {
            "id"        : 13,
            "image"     : "assets/img/discrimination/hoja.png",
            "title"      : "Hoja de papel",
            "category"  : "papeleria"
        },
        {
            "id"        : 14,
            "image"     : "assets/img/discrimination/sacapuntas.png",
            "title"      : "Sacapuntas",
            "category"  : "papeleria"
        },
        {
            "id"        : 15,
            "image"     : "assets/img/discrimination/triciclo.png",
            "title"      : "Triciclo",
            "category"  : "transporte"
        },
        {
            "id"        : 16,
            "image"     : "assets/img/discrimination/tenedor.png",
            "title"      : "Tenedor",
            "category"  : "cubierto"
        },
        {
            "id"        : 17,
            "image"     : "assets/img/discrimination/bicicleta.png",
            "title"      : "Bicicleta",
            "category"  : "transporte"
        },
        {
            "id"        : 18,
            "image"     : "assets/img/discrimination/puerta.png",
            "title"      : "Puerta",
            "category"  : "madera"
        },
        {
            "id"        : 19,
            "image"     : "assets/img/discrimination/manzana.png",
            "title"      : "Manzana",
            "category"  : "fruta"
        },
        {
            "id"        : 20,
            "image"     : "assets/img/discrimination/pina.png",
            "title"      : "Piña",
            "category"  : "fruta"
        },
        {
            "id"        : 21,
            "image"     : "assets/img/discrimination/silla.png",
            "title"      : "Silla",
            "category"  : "madera"
        },
        {
            "id"        : 22,
            "image"     : "assets/img/discrimination/mesa.png",
            "title"      : "Mesa",
            "category"  : "madera"
        },
        {
            "id"        : 23,
            "image"     : "assets/img/discrimination/maestra.png",
            "title"      : "Maestra",
            "category"  : "oficio"
        },
        {
            "id"        : 24,
            "image"     : "assets/img/discrimination/cuchara.png",
            "title"      : "Cuchara",
            "category"  : "cubierto"
        },
        {
            "id"        : 25,
            "image"     : "assets/img/discrimination/lapiz.png",
            "title"      : "Lápiz",
            "category"  : "papeleria"
        },
        {
            "id"        : 26,
            "image"     : "assets/img/discrimination/libreta.png",
            "title"      : "Libreta",
            "category"  : "papeleria"
        },
        {
            "id"        : 27,
            "image"     : "assets/img/discrimination/carpintero.png",
            "title"      : "Carpintero",
            "category"  : "oficio"
        },
        {
            "id"        : 28,
            "image"     : "assets/img/discrimination/zapatero.gif",
            "title"      : "Zapatero",
            "category"  : "oficio"
        },
        {
            "id"        : 29,
            "image"     : "assets/img/discrimination/sueter.png",
            "title"      : "Suéter",
            "category"  : "prenda"
        },
        {
            "id"        : 30,
            "image"     : "assets/img/discrimination/arcoiris.png",
            "title"      : "Arcoiris",
            "category"  : "cielo"
        },
        {
            "id"        : 31,
            "image"     : "assets/img/discrimination/tijeras.png",
            "title"      : "Tijeras",
            "category"  : "papeleria"
        },
        {
            "id"        : 32,
            "image"     : "assets/img/discrimination/hoja.png",
            "title"      : "Hoja de papel",
            "category"  : "papeleria"
        },
        {
            "id"        : 33,
            "image"     : "assets/img/discrimination/pera.png",
            "title"      : "Pera",
            "category"  : "fruta"
        },
        {
            "id"        : 34,
            "image"     : "assets/img/discrimination/luna.png",
            "title"      : "Luna",
            "category"  : "cielo"
        },
        {
            "id"        : 35,
            "image"     : "assets/img/discrimination/manzana.png",
            "title"      : "Manzana",
            "category"  : "fruta"
        },
        {
            "id"        : 36,
            "image"     : "assets/img/discrimination/sueter.png",
            "title"      : "Suéter",
            "category"  : "prenda"
        },
        {
            "id"        : 37,
            "image"     : "assets/img/discrimination/bufanda.png",
            "title"      : "Bufanda",
            "category"  : "prenda"
        },
        {
            "id"        : 38,
            "image"     : "assets/img/discrimination/hoja.png",
            "title"      : "Hoja de papel",
            "category"  : "papeleria"
        },
        {
            "id"        : 39,
            "image"     : "assets/img/discrimination/maestra.png",
            "title"      : "Maestra",
            "category"  : "oficio"
        },
        {
            "id"        : 40,
            "image"     : "assets/img/discrimination/mesa.png",
            "title"      : "Mesa",
            "category"  : "madera"
        },
        {
            "id"        : 41,
            "image"     : "assets/img/discrimination/bombero.png",
            "title"      : "Bombero",
            "category"  : "oficio"
        },
        {
            "id"        : 42,
            "image"     : "assets/img/discrimination/lapiz.png",
            "title"      : "Lápiz",
            "category"  : "papeleria"
        },
        {
            "id"        : 43,
            "image"     : "assets/img/discrimination/automovil.png",
            "title"      : "Automóvil",
            "category"  : "transporte"
        },
        {
            "id"        : 44,
            "image"     : "assets/img/discrimination/triciclo.png",
            "title"      : "Triciclo",
            "category"  : "transporte"
        }
    ]
}